pybes3-0.3.14.dist-info/RECORD
pybes3-0.3.14.dist-info/WHEEL
pybes3-0.3.14.dist-info/METADATA
pybes3-0.3.14.dist-info/licenses/LICENSE
pybes3/_version.py
pybes3/_cache_numba.py
pybes3/__init__.py
pybes3/typing.py
pybes3/_utils.py
pybes3/tracks/helix.py
pybes3/tracks/__init__.py
pybes3/detectors/digi_id.py
pybes3/detectors/__init__.py
pybes3/detectors/geometry/emc_geom.npz
pybes3/detectors/geometry/__init__.py
pybes3/detectors/geometry/mdc_geom.npz
pybes3/detectors/geometry/emc.py
pybes3/detectors/geometry/mdc.py
pybes3/besio/root_io.py
pybes3/besio/__init__.py
pybes3/besio/besio_cpp.pyi
pybes3/besio/raw_io.py
pybes3/besio/besio_cpp.cpython-311-darwin.so
pybes3/besio/cpp/raw_io.hh
pybes3/besio/cpp/CMakeLists.txt
pybes3/besio/cpp/besio_cpp.cc
pybes3/besio/cpp/raw_io.cc
pybes3/besio/cpp/root_io.hh
