Metadata-Version: 2.2
Name: pybes3
Version: 0.3.14
Summary: Unofficial Python module for BES3
Author-Email: Mingrun Li <mrun_lee@foxmail.com>
Classifier: Development Status :: 3 - Alpha
Classifier: Intended Audience :: Developers
Classifier: Intended Audience :: Science/Research
Classifier: License :: OSI Approved :: MIT License
Classifier: Programming Language :: C++
Classifier: Programming Language :: Python
Classifier: Programming Language :: Python :: 3
Classifier: Programming Language :: Python :: 3.9
Classifier: Programming Language :: Python :: 3.10
Classifier: Programming Language :: Python :: 3.11
Classifier: Programming Language :: Python :: 3.12
Classifier: Programming Language :: Python :: 3.13
Classifier: Operating System :: OS Independent
Project-URL: Homepage, https://github.com/mrzimu/pybes3
Project-URL: Documentation, https://pybes3.readthedocs.io/en/stable/
Requires-Python: <3.14,>=3.9
Requires-Dist: uproot>=5.6.8
Requires-Dist: awkward
Requires-Dist: numba
Requires-Dist: vector!=1.7.0
Requires-Dist: uproot-custom<2.2,>=2.1.1
